peterparser/__init__.py
peterparser/peterparser.py
peterparser-1.0.0.dist-info/LICENSE
peterparser-1.0.0.dist-info/METADATA
peterparser-1.0.0.dist-info/WHEEL
peterparser-1.0.0.dist-info/top_level.txt
peterparser-1.0.0.dist-info/RECORD
