Metadata-Version: 2.1
Name: peterparser
Version: 1.0.0
Summary: A lightweight Python parser optimized for blockchain and DeFi applications. Designed to read and write complex configuration files that include lists and dictionaries, facilitating seamless smart contract interactions in Web3 environments.
Home-page: https://github.com/deefifofun/peterparser
Author: DeeFiFoFun
Author-email: dev@deefifofun.xyz
Requires-Python: >=3.10
License-File: LICENSE
